Metadata-Version: 2.1
Name: randomouse
Version: 0.0.6
Summary: A package that will run random mouse movement
Home-page: http://pypi.python.org/pypi/randomouse/
Author: Mark Prado
Author-email: otsukaranz@gmail.com
License: LICENSE
Platform: UNKNOWN
Classifier: Development Status :: 4 - Beta
Classifier: Environment :: Win32 (MS Windows)
Classifier: Topic :: Utilities
